LICENSE
govuk_tech_docs_sphinx_theme/README.md
govuk_tech_docs_sphinx_theme/__init__.py
govuk_tech_docs_sphinx_theme/components/__init__.py
govuk_tech_docs_sphinx_theme/components/notification_banner.py
govuk_tech_docs_sphinx_theme/components/warning_text.py
govuk_tech_docs_sphinx_theme/contribution_banner.html
govuk_tech_docs_sphinx_theme/footer.html
govuk_tech_docs_sphinx_theme/header_logo.html
govuk_tech_docs_sphinx_theme/header_navigation.html
govuk_tech_docs_sphinx_theme/layout.html
govuk_tech_docs_sphinx_theme/search.html
govuk_tech_docs_sphinx_theme/searchbox.html
govuk_tech_docs_sphinx_theme/sidebar.html
govuk_tech_docs_sphinx_theme/static/assets/govuk/assets/fonts/bold-affa96571d-v2.woff
govuk_tech_docs_sphinx_theme/static/assets/govuk/assets/fonts/bold-b542beb274-v2.woff2
govuk_tech_docs_sphinx_theme/static/assets/govuk/assets/fonts/light-94a07e06a1-v2.woff2
govuk_tech_docs_sphinx_theme/static/assets/govuk/assets/fonts/light-f591b13f7d-v2.woff
govuk_tech_docs_sphinx_theme/static/assets/govuk/assets/images/favicon.ico
govuk_tech_docs_sphinx_theme/static/assets/govuk/assets/images/govuk-apple-touch-icon-152x152.png
govuk_tech_docs_sphinx_theme/static/assets/govuk/assets/images/govuk-apple-touch-icon-167x167.png
govuk_tech_docs_sphinx_theme/static/assets/govuk/assets/images/govuk-apple-touch-icon-180x180.png
govuk_tech_docs_sphinx_theme/static/assets/govuk/assets/images/govuk-apple-touch-icon.png
govuk_tech_docs_sphinx_theme/static/assets/govuk/assets/images/govuk-crest-2x.png
govuk_tech_docs_sphinx_theme/static/assets/govuk/assets/images/govuk-crest.png
govuk_tech_docs_sphinx_theme/static/assets/govuk/assets/images/govuk-logotype-crown.png
govuk_tech_docs_sphinx_theme/static/assets/govuk/assets/images/govuk-mask-icon.svg
govuk_tech_docs_sphinx_theme/static/assets/govuk/assets/images/govuk-opengraph-image.png
govuk_tech_docs_sphinx_theme/static/favicon.ico
govuk_tech_docs_sphinx_theme/static/images/anchored-heading-icon-2x.png
govuk_tech_docs_sphinx_theme-1.0.0.dist-info/LICENSE
govuk_tech_docs_sphinx_theme-1.0.0.dist-info/WHEEL
govuk_tech_docs_sphinx_theme-1.0.0.dist-info/METADATA
govuk_tech_docs_sphinx_theme-1.0.0.dist-info/RECORD
