Metadata-Version: 2.1
Name: govuk-tech-docs-sphinx-theme
Version: 1.0.0
Summary: A Sphinx theme to replicate the GOV.UK Tech Docs Template.
Home-page: https://github.com/ukgovdatascience/govuk-tech-docs-sphinx-theme
License: MIT
Keywords: sphinx,theme
Author: ukgovdatascience
Author-email: gds-data-science@digital.cabinet-office.gov.uk
Requires-Python: >=3.6.1,<4.0.0
Classifier: Framework :: Sphinx
Classifier: Framework :: Sphinx :: Theme
Classifier: License :: OSI Approved :: MIT License
Classifier: Operating System :: OS Independent
Classifier: Programming Language :: Python :: 3
Classifier: Programming Language :: Python :: 3.7
Classifier: Programming Language :: Python :: 3.8
Classifier: Programming Language :: Python :: 3.9
Requires-Dist: Sphinx (>=4.0.2,<5.0.0)
Project-URL: Documentation, https://ukgovdatascience.github.io/govuk-tech-docs-sphinx-theme
Project-URL: Repository, https://github.com/ukgovdatascience/govuk-tech-docs-sphinx-theme
